copernicusmarine/__init__.py
copernicusmarine/_version.py
copernicusmarine/aioretry/LICENSE
copernicusmarine/aioretry/__init__.py
copernicusmarine/aioretry/retry.py
copernicusmarine/catalogue_parser/__init__.py
copernicusmarine/catalogue_parser/catalogue_parser.py
copernicusmarine/catalogue_parser/request_structure.py
copernicusmarine/command_line_interface/__init__.py
copernicusmarine/command_line_interface/copernicus_marine.py
copernicusmarine/command_line_interface/exception_handler.py
copernicusmarine/command_line_interface/group_describe.py
copernicusmarine/command_line_interface/group_get.py
copernicusmarine/command_line_interface/group_login.py
copernicusmarine/command_line_interface/group_subset.py
copernicusmarine/command_line_interface/utils.py
copernicusmarine/core_functions/credentials_utils.py
copernicusmarine/core_functions/custom_open_zarr.py
copernicusmarine/core_functions/deprecated.py
copernicusmarine/core_functions/deprecated_options.py
copernicusmarine/core_functions/describe.py
copernicusmarine/core_functions/environment_variables.py
copernicusmarine/core_functions/exceptions.py
copernicusmarine/core_functions/get.py
copernicusmarine/core_functions/login.py
copernicusmarine/core_functions/models.py
copernicusmarine/core_functions/services_utils.py
copernicusmarine/core_functions/sessions.py
copernicusmarine/core_functions/subset.py
copernicusmarine/core_functions/utils.py
copernicusmarine/core_functions/versions_verifier.py
copernicusmarine/download_functions/common_download.py
copernicusmarine/download_functions/download_arco_series.py
copernicusmarine/download_functions/download_original_files.py
copernicusmarine/download_functions/subset_parameters.py
copernicusmarine/download_functions/subset_xarray.py
copernicusmarine/download_functions/utils.py
copernicusmarine/logging_conf.py
copernicusmarine/python_interface/describe.py
copernicusmarine/python_interface/exception_handler.py
copernicusmarine/python_interface/get.py
maresb_copernicusmarine_unpin_numpy-0.1.3.3.post1.dist-info/LICENSE.txt
maresb_copernicusmarine_unpin_numpy-0.1.3.3.post1.dist-info/METADATA
maresb_copernicusmarine_unpin_numpy-0.1.3.3.post1.dist-info/WHEEL
maresb_copernicusmarine_unpin_numpy-0.1.3.3.post1.dist-info/entry_points.txt
maresb_copernicusmarine_unpin_numpy-0.1.3.3.post1.dist-info/RECORD
