Metadata-Version: 2.1
Name: maresb-copernicusmarine-unpin-numpy
Version: 0.1.3.3.post1
Summary: A temporary workaround to use Copernicus Marine with Numpy v2
License: EUPL-1.2
Author: Copernicus Marine User Support
Author-email: servicedesk.cmems@mercator-ocean.eu
Requires-Python: >=3.9,<3.13
Classifier: License :: OSI Approved :: European Union Public Licence 1.2 (EUPL 1.2)
Classifier: Programming Language :: Python :: 3
Classifier: Programming Language :: Python :: 3.9
Classifier: Programming Language :: Python :: 3.10
Classifier: Programming Language :: Python :: 3.11
Classifier: Programming Language :: Python :: 3.12
Requires-Dist: aiohttp (>=3.9.4,<3.10.0)
Requires-Dist: boto3 (>=1.25)
Requires-Dist: cachier (>=2.2.1)
Requires-Dist: click (>=8.0.4)
Requires-Dist: dask (>=2022)
Requires-Dist: lxml (>=4.9.0)
Requires-Dist: nest-asyncio (>=1.5.8)
Requires-Dist: netCDF4 (>=1.5.4)
Requires-Dist: numpy (>=1.23.0)
Requires-Dist: pystac (>=1.8.3)
Requires-Dist: requests (>=2.27.1)
Requires-Dist: semver (>=3.0.2)
Requires-Dist: setuptools (>=68.2.2)
Requires-Dist: tqdm (>=4.65.0)
Requires-Dist: xarray (>=2023.4.0)
Requires-Dist: zarr (>=2.13.3)
